<?xml version="1.0" encoding="UTF-8"?>
<aisweb>
	<rotaer pagesize="10" total="2">
		<item ciad_id="6193">
			<id>0246c52c-8800-4faf-bde4-9d68f10aa25d</id>
			<type>AD</type>
			<AeroCode>SBRF</AeroCode>
			<ciad>PE0001</ciad>
			<name>
				<![CDATA[Guararapes - Gilberto Freyre]]>
			</name>
			<city>
				<![CDATA[Recife]]>
			</city>
			<uf>PE</uf>
			<lng>-34.922777777778</lng>
			<lat>-8.126388888889</lat>
			<dt>2023-10-17</dt>
		</item>
		<item ciad_id="7638">
			<id>766b9657-fd37-469f-aa63-2efb6c3e1bad</id>
			<type>AD</type>
			<AeroCode>SBBV</AeroCode>
			<ciad>RR0001</ciad>
			<name>
				<![CDATA[Atlas Brasil Cantanhede]]>
			</name>
			<city>
				<![CDATA[Boa Vista]]>
			</city>
			<uf>RR</uf>
			<lng>-60.692222222222</lng>
			<lat>2.841388888889</lat>
			<dt>2023-09-21</dt>
		</item>
	</rotaer>
</aisweb>
